commons/__init__.py
commons/utils.py
viemind_test_c0mmon-0.1.0.dist-info/METADATA
viemind_test_c0mmon-0.1.0.dist-info/WHEEL
viemind_test_c0mmon-0.1.0.dist-info/RECORD
