Metadata-Version: 2.3
Name: viemind-test-c0mmon
Version: 0.1.0
Summary: Shared utilities for services
Author: Duy
Author-email: thanhduy@viemind.ai
Requires-Python: ==3.10.0
Classifier: Programming Language :: Python :: 3
Classifier: Programming Language :: Python :: 3.10
